magicdef/__init__.py
magicdef-0.1.0.dist-info/licenses/LICENSE
magicdef-0.1.0.dist-info/METADATA
magicdef-0.1.0.dist-info/WHEEL
magicdef-0.1.0.dist-info/top_level.txt
magicdef-0.1.0.dist-info/RECORD
