Metadata-Version: 2.4
Name: magicdef
Version: 0.1.0
Summary: coming soon
Author: Olaf Pedersen
Author-email: olaf.acount@gmail.com
Requires-Python: >=3.10
License-File: LICENSE
Dynamic: author
Dynamic: author-email
Dynamic: license-file
Dynamic: requires-python
Dynamic: summary
